nmrformd/NMR.py
nmrformd/__init__.py
nmrformd/utilities.py
nmrformd-0.1.0.dist-info/LICENSE.txt
nmrformd-0.1.0.dist-info/METADATA
nmrformd-0.1.0.dist-info/WHEEL
nmrformd-0.1.0.dist-info/top_level.txt
nmrformd-0.1.0.dist-info/RECORD
