Metadata-Version: 2.1
Name: nmrformd
Version: 0.1.0
Summary: Calculate NMR relaxation time from                    molecular dynamics trajectory file
Home-page: https://github.com/simongravelle/nmrformd
Author: Simon Gravelle
Author-email: simon.gravelle@live.fr
License: GNU GENERAL PUBLIC LICENSE
Download-URL: https://github.com/simongravelle/nmrformd/releases/download/v0.1.0/nmrformd-0.1.0.tar.gz
Platform: UNKNOWN
Requires-Dist: mdanalysis
Requires-Dist: numpy
Requires-Dist: pytest
Requires-Dist: scipy
